<?xml version="1.0"?>
<opencv_storage>
<Frame>
  <ID>184681</ID>
  <Images>
    <nImages>2</nImages>
    <RigthImage>
      <Hands>
        <nHands>1</nHands>
        <Right>
          <Center type_id="opencv-matrix">
            <rows>1</rows>
            <cols>3</cols>
            <dt>f</dt>
            <data>
              7.93039656e+000 1.85418900e+002 6.68694763e+001</data></Center>
          <Normal type_id="opencv-matrix">
            <rows>1</rows>
            <cols>3</cols>
            <dt>f</dt>
            <data>
              -8.07325661e-001 -3.50347579e-001 -4.74849254e-001</data></Normal>
          <Direction type_id="opencv-matrix">
            <rows>1</rows>
            <cols>3</cols>
            <dt>f</dt>
            <data>
              1.44941926e-001 6.62305415e-001 -7.35080540e-001</data></Direction>
          <Velocity type_id="opencv-matrix">
            <rows>1</rows>
            <cols>3</cols>
            <dt>f</dt>
            <data>
              -3.48392029e+002 2.75054131e+001 1.16446053e+002</data></Velocity>
          <SphereCenter type_id="opencv-matrix">
            <rows>1</rows>
            <cols>3</cols>
            <dt>f</dt>
            <data>
              -2.09728947e+001 1.81041321e+002 3.92020493e+001</data></SphereCenter>
          <Confidence>3.2099744677543640e-001</Confidence>
          <PinchStrength>1.</PinchStrength>
          <GrabStrength>1.</GrabStrength>
          <SphereRadius>3.4005115509033203e+001</SphereRadius>
          <Fingers>
            <nFingers>5</nFingers>
            <Thumb>
              <Type>0</Type>
              <isExtended>0</isExtended>
              <TipPosition type_id="opencv-matrix">
                <rows>1</rows>
                <cols>3</cols>
                <dt>f</dt>
                <data>
                  -3.42542610e+001 1.86867523e+002 4.46144333e+001</data></TipPosition>
              <TipDirection type_id="opencv-matrix">
                <rows>1</rows>
                <cols>3</cols>
                <dt>f</dt>
                <data>
                  -1.27849236e-001 1.83671623e-001 -9.74638045e-001</data></TipDirection>
              <TipVelocity type_id="opencv-matrix">
                <rows>1</rows>
                <cols>3</cols>
                <dt>f</dt>
                <data>
                  -3.25204590e+002 -1.08750275e+002 1.71174805e+002</data></TipVelocity>
              <TipLength>5.2116371154785156e+001</TipLength>
              <dipPosition type_id="opencv-matrix">
                <rows>1</rows>
                <cols>3</cols>
                <dt>f</dt>
                <data>
                  -3.97878380e+001 2.01536087e+002 5.36646461e+001</data></dipPosition>
              <pipPosition type_id="opencv-matrix">
                <rows>1</rows>
                <cols>3</cols>
                <dt>f</dt>
                <data>
                  -3.54287415e+001 1.95273697e+002 8.68955154e+001</data></pipPosition>
              <mcpPosition type_id="opencv-matrix">
                <rows>1</rows>
                <cols>3</cols>
                <dt>f</dt>
                <data>
                  -1.75709324e+001 1.58949600e+002 1.16108963e+002</data></mcpPosition></Thumb>
            <Index>
              <Type>1</Type>
              <isExtended>0</isExtended>
              <TipPosition type_id="opencv-matrix">
                <rows>1</rows>
                <cols>3</cols>
                <dt>f</dt>
                <data>
                  -3.39274979e+001 1.76652390e+002 6.55996552e+001</data></TipPosition>
              <TipDirection type_id="opencv-matrix">
                <rows>1</rows>
                <cols>3</cols>
                <dt>f</dt>
                <data>
                  -1.22535340e-001 -8.27301383e-001 5.48231244e-001</data></TipDirection>
              <TipVelocity type_id="opencv-matrix">
                <rows>1</rows>
                <cols>3</cols>
                <dt>f</dt>
                <data>
                  -3.41074677e+002 -1.15132393e+002 1.39887360e+002</data></TipVelocity>
              <TipLength>5.8807510375976563e+001</TipLength>
              <dipPosition type_id="opencv-matrix">
                <rows>1</rows>
                <cols>3</cols>
                <dt>f</dt>
                <data>
                  -3.88608131e+001 1.83627670e+002 5.53068542e+001</data></dipPosition>
              <pipPosition type_id="opencv-matrix">
                <rows>1</rows>
                <cols>3</cols>
                <dt>f</dt>
                <data>
                  -3.58990822e+001 2.03623871e+002 4.20558853e+001</data></pipPosition>
              <mcpPosition type_id="opencv-matrix">
                <rows>1</rows>
                <cols>3</cols>
                <dt>f</dt>
                <data>
                  -1.02323902e+000 2.19314728e+002 6.16324120e+001</data></mcpPosition></Index>
            <Middle>
              <Type>2</Type>
              <isExtended>0</isExtended>
              <TipPosition type_id="opencv-matrix">
                <rows>1</rows>
                <cols>3</cols>
                <dt>f</dt>
                <data>
                  -3.26310158e+001 1.66319672e+002 6.51892700e+001</data></TipPosition>
              <TipDirection type_id="opencv-matrix">
                <rows>1</rows>
                <cols>3</cols>
                <dt>f</dt>
                <data>
                  -2.67192662e-001 -6.88372314e-001 6.74352765e-001</data></TipDirection>
              <TipVelocity type_id="opencv-matrix">
                <rows>1</rows>
                <cols>3</cols>
                <dt>f</dt>
                <data>
                  -3.07499359e+002 -1.11347260e+002 1.34380981e+002</data></TipVelocity>
              <TipLength>6.7006439208984375e+001</TipLength>
              <dipPosition type_id="opencv-matrix">
                <rows>1</rows>
                <cols>3</cols>
                <dt>f</dt>
                <data>
                  -3.69587936e+001 1.73240250e+002 5.27118225e+001</data></dipPosition>
              <pipPosition type_id="opencv-matrix">
                <rows>1</rows>
                <cols>3</cols>
                <dt>f</dt>
                <data>
                  -2.93607979e+001 1.92815094e+002 3.35356598e+001</data></pipPosition>
              <mcpPosition type_id="opencv-matrix">
                <rows>1</rows>
                <cols>3</cols>
                <dt>f</dt>
                <data>
                  1.33349819e+001 2.05559097e+002 5.19187813e+001</data></mcpPosition></Middle>
            <Ring>
              <Type>3</Type>
              <isExtended>0</isExtended>
              <TipPosition type_id="opencv-matrix">
                <rows>1</rows>
                <cols>3</cols>
                <dt>f</dt>
                <data>
                  -2.46778793e+001 1.54968582e+002 6.34082756e+001</data></TipPosition>
              <TipDirection type_id="opencv-matrix">
                <rows>1</rows>
                <cols>3</cols>
                <dt>f</dt>
                <data>
                  -3.79941046e-001 -5.67658186e-001 7.30348527e-001</data></TipDirection>
              <TipVelocity type_id="opencv-matrix">
                <rows>1</rows>
                <cols>3</cols>
                <dt>f</dt>
                <data>
                  -2.59616638e+002 -9.11890030e+001 1.32243530e+002</data></TipVelocity>
              <TipLength>6.4428482055664063e+001</TipLength>
              <dipPosition type_id="opencv-matrix">
                <rows>1</rows>
                <cols>3</cols>
                <dt>f</dt>
                <data>
                  -2.62626915e+001 1.61092194e+002 5.06701355e+001</data></dipPosition>
              <pipPosition type_id="opencv-matrix">
                <rows>1</rows>
                <cols>3</cols>
                <dt>f</dt>
                <data>
                  -1.57375650e+001 1.76817474e+002 3.04380188e+001</data></pipPosition>
              <mcpPosition type_id="opencv-matrix">
                <rows>1</rows>
                <cols>3</cols>
                <dt>f</dt>
                <data>
                  2.49015808e+001 1.86812790e+002 4.60847359e+001</data></mcpPosition></Ring>
            <Pinky>
              <Type>4</Type>
              <isExtended>0</isExtended>
              <TipPosition type_id="opencv-matrix">
                <rows>1</rows>
                <cols>3</cols>
                <dt>f</dt>
                <data>
                  -1.20980473e+001 1.49735336e+002 5.33787041e+001</data></TipPosition>
              <TipDirection type_id="opencv-matrix">
                <rows>1</rows>
                <cols>3</cols>
                <dt>f</dt>
                <data>
                  -5.23155034e-001 -4.92267877e-001 6.95687592e-001</data></TipDirection>
              <TipVelocity type_id="opencv-matrix">
                <rows>1</rows>
                <cols>3</cols>
                <dt>f</dt>
                <data>
                  -2.45543182e+002 -4.61368256e+001 1.20041824e+002</data></TipVelocity>
              <TipLength>5.0510734558105469e+001</TipLength>
              <dipPosition type_id="opencv-matrix">
                <rows>1</rows>
                <cols>3</cols>
                <dt>f</dt>
                <data>
                  -1.19380808e+001 1.55849365e+002 4.16639671e+001</data></dipPosition>
              <pipPosition type_id="opencv-matrix">
                <rows>1</rows>
                <cols>3</cols>
                <dt>f</dt>
                <data>
                  -1.70579696e+000 1.65477539e+002 2.80571537e+001</data></pipPosition>
              <mcpPosition type_id="opencv-matrix">
                <rows>1</rows>
                <cols>3</cols>
                <dt>f</dt>
                <data>
                  3.12844639e+001 1.67102402e+002 4.06775932e+001</data></mcpPosition></Pinky></Fingers></Right></Hands></RigthImage>
    <LeftImage>
      <Hands>
        <nHands>1</nHands>
        <Right>
          <Center type_id="opencv-matrix">
            <rows>1</rows>
            <cols>3</cols>
            <dt>f</dt>
            <data>
              7.93039656e+000 1.85418900e+002 6.68694763e+001</data></Center>
          <Normal type_id="opencv-matrix">
            <rows>1</rows>
            <cols>3</cols>
            <dt>f</dt>
            <data>
              -8.07325661e-001 -3.50347579e-001 -4.74849254e-001</data></Normal>
          <Direction type_id="opencv-matrix">
            <rows>1</rows>
            <cols>3</cols>
            <dt>f</dt>
            <data>
              1.44941926e-001 6.62305415e-001 -7.35080540e-001</data></Direction>
          <Velocity type_id="opencv-matrix">
            <rows>1</rows>
            <cols>3</cols>
            <dt>f</dt>
            <data>
              -3.48392029e+002 2.75054131e+001 1.16446053e+002</data></Velocity>
          <SphereCenter type_id="opencv-matrix">
            <rows>1</rows>
            <cols>3</cols>
            <dt>f</dt>
            <data>
              -2.09728947e+001 1.81041321e+002 3.92020493e+001</data></SphereCenter>
          <Confidence>3.2099744677543640e-001</Confidence>
          <PinchStrength>1.</PinchStrength>
          <GrabStrength>1.</GrabStrength>
          <SphereRadius>3.4005115509033203e+001</SphereRadius>
          <Fingers>
            <nFingers>5</nFingers>
            <Thumb>
              <Type>0</Type>
              <isExtended>0</isExtended>
              <TipPosition type_id="opencv-matrix">
                <rows>1</rows>
                <cols>3</cols>
                <dt>f</dt>
                <data>
                  -3.42542610e+001 1.86867523e+002 4.46144333e+001</data></TipPosition>
              <TipDirection type_id="opencv-matrix">
                <rows>1</rows>
                <cols>3</cols>
                <dt>f</dt>
                <data>
                  -1.27849236e-001 1.83671623e-001 -9.74638045e-001</data></TipDirection>
              <TipVelocity type_id="opencv-matrix">
                <rows>1</rows>
                <cols>3</cols>
                <dt>f</dt>
                <data>
                  -3.25204590e+002 -1.08750275e+002 1.71174805e+002</data></TipVelocity>
              <TipLength>5.2116371154785156e+001</TipLength>
              <dipPosition type_id="opencv-matrix">
                <rows>1</rows>
                <cols>3</cols>
                <dt>f</dt>
                <data>
                  -3.97878380e+001 2.01536087e+002 5.36646461e+001</data></dipPosition>
              <pipPosition type_id="opencv-matrix">
                <rows>1</rows>
                <cols>3</cols>
                <dt>f</dt>
                <data>
                  -3.54287415e+001 1.95273697e+002 8.68955154e+001</data></pipPosition>
              <mcpPosition type_id="opencv-matrix">
                <rows>1</rows>
                <cols>3</cols>
                <dt>f</dt>
                <data>
                  -1.75709324e+001 1.58949600e+002 1.16108963e+002</data></mcpPosition></Thumb>
            <Index>
              <Type>1</Type>
              <isExtended>0</isExtended>
              <TipPosition type_id="opencv-matrix">
                <rows>1</rows>
                <cols>3</cols>
                <dt>f</dt>
                <data>
                  -3.39274979e+001 1.76652390e+002 6.55996552e+001</data></TipPosition>
              <TipDirection type_id="opencv-matrix">
                <rows>1</rows>
                <cols>3</cols>
                <dt>f</dt>
                <data>
                  -1.22535340e-001 -8.27301383e-001 5.48231244e-001</data></TipDirection>
              <TipVelocity type_id="opencv-matrix">
                <rows>1</rows>
                <cols>3</cols>
                <dt>f</dt>
                <data>
                  -3.41074677e+002 -1.15132393e+002 1.39887360e+002</data></TipVelocity>
              <TipLength>5.8807510375976563e+001</TipLength>
              <dipPosition type_id="opencv-matrix">
                <rows>1</rows>
                <cols>3</cols>
                <dt>f</dt>
                <data>
                  -3.88608131e+001 1.83627670e+002 5.53068542e+001</data></dipPosition>
              <pipPosition type_id="opencv-matrix">
                <rows>1</rows>
                <cols>3</cols>
                <dt>f</dt>
                <data>
                  -3.58990822e+001 2.03623871e+002 4.20558853e+001</data></pipPosition>
              <mcpPosition type_id="opencv-matrix">
                <rows>1</rows>
                <cols>3</cols>
                <dt>f</dt>
                <data>
                  -1.02323902e+000 2.19314728e+002 6.16324120e+001</data></mcpPosition></Index>
            <Middle>
              <Type>2</Type>
              <isExtended>0</isExtended>
              <TipPosition type_id="opencv-matrix">
                <rows>1</rows>
                <cols>3</cols>
                <dt>f</dt>
                <data>
                  -3.26310158e+001 1.66319672e+002 6.51892700e+001</data></TipPosition>
              <TipDirection type_id="opencv-matrix">
                <rows>1</rows>
                <cols>3</cols>
                <dt>f</dt>
                <data>
                  -2.67192662e-001 -6.88372314e-001 6.74352765e-001</data></TipDirection>
              <TipVelocity type_id="opencv-matrix">
                <rows>1</rows>
                <cols>3</cols>
                <dt>f</dt>
                <data>
                  -3.07499359e+002 -1.11347260e+002 1.34380981e+002</data></TipVelocity>
              <TipLength>6.7006439208984375e+001</TipLength>
              <dipPosition type_id="opencv-matrix">
                <rows>1</rows>
                <cols>3</cols>
                <dt>f</dt>
                <data>
                  -3.69587936e+001 1.73240250e+002 5.27118225e+001</data></dipPosition>
              <pipPosition type_id="opencv-matrix">
                <rows>1</rows>
                <cols>3</cols>
                <dt>f</dt>
                <data>
                  -2.93607979e+001 1.92815094e+002 3.35356598e+001</data></pipPosition>
              <mcpPosition type_id="opencv-matrix">
                <rows>1</rows>
                <cols>3</cols>
                <dt>f</dt>
                <data>
                  1.33349819e+001 2.05559097e+002 5.19187813e+001</data></mcpPosition></Middle>
            <Ring>
              <Type>3</Type>
              <isExtended>0</isExtended>
              <TipPosition type_id="opencv-matrix">
                <rows>1</rows>
                <cols>3</cols>
                <dt>f</dt>
                <data>
                  -2.46778793e+001 1.54968582e+002 6.34082756e+001</data></TipPosition>
              <TipDirection type_id="opencv-matrix">
                <rows>1</rows>
                <cols>3</cols>
                <dt>f</dt>
                <data>
                  -3.79941046e-001 -5.67658186e-001 7.30348527e-001</data></TipDirection>
              <TipVelocity type_id="opencv-matrix">
                <rows>1</rows>
                <cols>3</cols>
                <dt>f</dt>
                <data>
                  -2.59616638e+002 -9.11890030e+001 1.32243530e+002</data></TipVelocity>
              <TipLength>6.4428482055664063e+001</TipLength>
              <dipPosition type_id="opencv-matrix">
                <rows>1</rows>
                <cols>3</cols>
                <dt>f</dt>
                <data>
                  -2.62626915e+001 1.61092194e+002 5.06701355e+001</data></dipPosition>
              <pipPosition type_id="opencv-matrix">
                <rows>1</rows>
                <cols>3</cols>
                <dt>f</dt>
                <data>
                  -1.57375650e+001 1.76817474e+002 3.04380188e+001</data></pipPosition>
              <mcpPosition type_id="opencv-matrix">
                <rows>1</rows>
                <cols>3</cols>
                <dt>f</dt>
                <data>
                  2.49015808e+001 1.86812790e+002 4.60847359e+001</data></mcpPosition></Ring>
            <Pinky>
              <Type>4</Type>
              <isExtended>0</isExtended>
              <TipPosition type_id="opencv-matrix">
                <rows>1</rows>
                <cols>3</cols>
                <dt>f</dt>
                <data>
                  -1.20980473e+001 1.49735336e+002 5.33787041e+001</data></TipPosition>
              <TipDirection type_id="opencv-matrix">
                <rows>1</rows>
                <cols>3</cols>
                <dt>f</dt>
                <data>
                  -5.23155034e-001 -4.92267877e-001 6.95687592e-001</data></TipDirection>
              <TipVelocity type_id="opencv-matrix">
                <rows>1</rows>
                <cols>3</cols>
                <dt>f</dt>
                <data>
                  -2.45543182e+002 -4.61368256e+001 1.20041824e+002</data></TipVelocity>
              <TipLength>5.0510734558105469e+001</TipLength>
              <dipPosition type_id="opencv-matrix">
                <rows>1</rows>
                <cols>3</cols>
                <dt>f</dt>
                <data>
                  -1.19380808e+001 1.55849365e+002 4.16639671e+001</data></dipPosition>
              <pipPosition type_id="opencv-matrix">
                <rows>1</rows>
                <cols>3</cols>
                <dt>f</dt>
                <data>
                  -1.70579696e+000 1.65477539e+002 2.80571537e+001</data></pipPosition>
              <mcpPosition type_id="opencv-matrix">
                <rows>1</rows>
                <cols>3</cols>
                <dt>f</dt>
                <data>
                  3.12844639e+001 1.67102402e+002 4.06775932e+001</data></mcpPosition></Pinky></Fingers></Right></Hands></LeftImage></Images></Frame>
</opencv_storage>
