{"table":[{"type":"3D","count":0,"x":48408,"y":65534,"z":4935},{"type":"3D","count":1,"x":48317,"y":65534,"z":6034},{"type":"3D","count":2,"x":48235,"y":65534,"z":7305},{"type":"3D","count":3,"x":48188,"y":65534,"z":8415},{"type":"3D","count":4,"x":48162,"y":65534,"z":9265},{"type":"3D","count":5,"x":48162,"y":65534,"z":9962},{"type":"3D","count":6,"x":48165,"y":65534,"z":10889},{"type":"3D","count":7,"x":48166,"y":65534,"z":12168},{"type":"3D","count":8,"x":48185,"y":65534,"z":13034},{"type":"3D","count":9,"x":48212,"y":65534,"z":13692},{"type":"3D","count":10,"x":48255,"y":65534,"z":14606},{"type":"3D","count":11,"x":48328,"y":65534,"z":15274},{"type":"3D","count":12,"x":48394,"y":65534,"z":15536},{"type":"3D","count":13,"x":48442,"y":65534,"z":15933},{"type":"3D","count":14,"x":48507,"y":65534,"z":16832},{"type":"3D","count":15,"x":48594,"y":65534,"z":17379},{"type":"3D","count":16,"x":48688,"y":65534,"z":17689},{"type":"3D","count":17,"x":48810,"y":65534,"z":17979},{"type":"3D","count":18,"x":48975,"y":65534,"z":18501},{"type":"3D","count":19,"x":49170,"y":65534,"z":18968},{"type":"3D","count":20,"x":49325,"y":65534,"z":19185},{"type":"3D","count":21,"x":49532,"y":65534,"z":19641},{"type":"3D","count":22,"x":49710,"y":65534,"z":20161},{"type":"3D","count":23,"x":49842,"y":65534,"z":20347},{"type":"3D","count":24,"x":49940,"y":65534,"z":20515},{"type":"3D","count":25,"x":50039,"y":65534,"z":21084},{"type":"3D","count":26,"x":50166,"y":65534,"z":21756},{"type":"3D","count":27,"x":50269,"y":65483,"z":21979},{"type":"3D","count":28,"x":50372,"y":65238,"z":22051},{"type":"3D","count":29,"x":50491,"y":64694,"z":22056},{"type":"3D","count":30,"x":50632,"y":63725,"z":22036},{"type":"3D","count":31,"x":50813,"y":62252,"z":21981},{"type":"3D","count":32,"x":51200,"y":58785,"z":21858},{"type":"3D","count":33,"x":52319,"y":51110,"z":21654},{"type":"3D","count":34,"x":55920,"y":34947,"z":20460},{"type":"3D","count":35,"x":56863,"y":28883,"z":19243},{"type":"3D","count":36,"x":57430,"y":25358,"z":18580},{"type":"3D","count":37,"x":58135,"y":21224,"z":17306},{"type":"3D","count":38,"x":59224,"y":17421,"z":16372},{"type":"3D","count":39,"x":60213,"y":15142,"z":15085},{"type":"3D","count":40,"x":61545,"y":12805,"z":13712},{"type":"3D","count":41,"x":62556,"y":10679,"z":12545},{"type":"3D","count":42,"x":63607,"y":7944,"z":11380},{"type":"3D","count":43,"x":64915,"y":5067,"z":9920},{"type":"3D","count":44,"x":65534,"y":2503,"z":8779},{"type":"3D","count":45,"x":65534,"y":0,"z":6924},{"type":"3D","count":46,"x":65534,"y":0,"z":5522},{"type":"3D","count":47,"x":65534,"y":0,"z":4380},{"type":"3D","count":48,"x":65534,"y":0,"z":3670},{"type":"3D","count":49,"x":65534,"y":0,"z":3636}]}