<?xml version="1.0"?>
<opencv_storage>
<Frame>
  <ID>498982</ID>
  <Images>
    <nImages>2</nImages>
    <RigthImage>
      <Hands>
        <nHands>1</nHands>
        <Right>
          <Center type_id="opencv-matrix">
            <rows>1</rows>
            <cols>3</cols>
            <dt>f</dt>
            <data>
              -5.89856300e+001 1.61372528e+002 -3.13172722e+000</data></Center>
          <Normal type_id="opencv-matrix">
            <rows>1</rows>
            <cols>3</cols>
            <dt>f</dt>
            <data>
              -1.95793584e-001 -8.40599716e-001 -5.05031645e-001</data></Normal>
          <Direction type_id="opencv-matrix">
            <rows>1</rows>
            <cols>3</cols>
            <dt>f</dt>
            <data>
              -2.09386364e-001 5.38958371e-001 -8.15892875e-001</data></Direction>
          <Velocity type_id="opencv-matrix">
            <rows>1</rows>
            <cols>3</cols>
            <dt>f</dt>
            <data>
              9.61543732e+001 -8.18312740e+000 6.61570892e+001</data></Velocity>
          <SphereCenter type_id="opencv-matrix">
            <rows>1</rows>
            <cols>3</cols>
            <dt>f</dt>
            <data>
              -8.81571579e+001 1.41621048e+002 -2.52005215e+001</data></SphereCenter>
          <Confidence>7.8935933113098145e-001</Confidence>
          <PinchStrength>0.</PinchStrength>
          <GrabStrength>3.7596240639686584e-001</GrabStrength>
          <SphereRadius>4.2725090026855469e+001</SphereRadius>
          <Fingers>
            <nFingers>5</nFingers>
            <Thumb>
              <Type>0</Type>
              <isExtended>1</isExtended>
              <TipPosition type_id="opencv-matrix">
                <rows>1</rows>
                <cols>3</cols>
                <dt>f</dt>
                <data>
                  -1.36189072e+002 1.54973999e+002 -6.45511329e-001</data></TipPosition>
              <TipDirection type_id="opencv-matrix">
                <rows>1</rows>
                <cols>3</cols>
                <dt>f</dt>
                <data>
                  -8.70011151e-001 2.78747350e-001 -4.06670064e-001</data></TipDirection>
              <TipVelocity type_id="opencv-matrix">
                <rows>1</rows>
                <cols>3</cols>
                <dt>f</dt>
                <data>
                  8.74364319e+001 5.60648918e+001 2.02645126e+002</data></TipVelocity>
              <TipLength>4.2449111938476562e+001</TipLength>
              <dipPosition type_id="opencv-matrix">
                <rows>1</rows>
                <cols>3</cols>
                <dt>f</dt>
                <data>
                  -1.22956001e+002 1.50613007e+002 3.33959699e+000</data></dipPosition>
              <pipPosition type_id="opencv-matrix">
                <rows>1</rows>
                <cols>3</cols>
                <dt>f</dt>
                <data>
                  -9.87948532e+001 1.42871902e+002 1.46332636e+001</data></pipPosition>
              <mcpPosition type_id="opencv-matrix">
                <rows>1</rows>
                <cols>3</cols>
                <dt>f</dt>
                <data>
                  -6.65231857e+001 1.32647064e+002 3.71517220e+001</data></mcpPosition></Thumb>
            <Index>
              <Type>1</Type>
              <isExtended>0</isExtended>
              <TipPosition type_id="opencv-matrix">
                <rows>1</rows>
                <cols>3</cols>
                <dt>f</dt>
                <data>
                  -7.92801285e+001 1.33877945e+002 -4.74600267e+000</data></TipPosition>
              <TipDirection type_id="opencv-matrix">
                <rows>1</rows>
                <cols>3</cols>
                <dt>f</dt>
                <data>
                  2.81607807e-001 -5.55764198e-001 7.82191277e-001</data></TipDirection>
              <TipVelocity type_id="opencv-matrix">
                <rows>1</rows>
                <cols>3</cols>
                <dt>f</dt>
                <data>
                  7.46353455e+001 4.47875977e+000 1.09914169e+002</data></TipVelocity>
              <TipLength>4.7899085998535156e+001</TipLength>
              <dipPosition type_id="opencv-matrix">
                <rows>1</rows>
                <cols>3</cols>
                <dt>f</dt>
                <data>
                  -8.29361496e+001 1.33888336e+002 -1.45152073e+001</data></dipPosition>
              <pipPosition type_id="opencv-matrix">
                <rows>1</rows>
                <cols>3</cols>
                <dt>f</dt>
                <data>
                  -8.84801483e+001 1.44829620e+002 -2.99141617e+001</data></pipPosition>
              <mcpPosition type_id="opencv-matrix">
                <rows>1</rows>
                <cols>3</cols>
                <dt>f</dt>
                <data>
                  -8.24410172e+001 1.74927765e+002 -1.31168127e+001</data></mcpPosition></Index>
            <Middle>
              <Type>2</Type>
              <isExtended>0</isExtended>
              <TipPosition type_id="opencv-matrix">
                <rows>1</rows>
                <cols>3</cols>
                <dt>f</dt>
                <data>
                  -6.92076187e+001 1.27979904e+002 -5.23018837e+000</data></TipPosition>
              <TipDirection type_id="opencv-matrix">
                <rows>1</rows>
                <cols>3</cols>
                <dt>f</dt>
                <data>
                  1.92439452e-001 -5.93580365e-001 7.81427801e-001</data></TipDirection>
              <TipVelocity type_id="opencv-matrix">
                <rows>1</rows>
                <cols>3</cols>
                <dt>f</dt>
                <data>
                  7.04503937e+001 -2.37938404e+000 9.74600754e+001</data></TipVelocity>
              <TipLength>5.4577163696289062e+001</TipLength>
              <dipPosition type_id="opencv-matrix">
                <rows>1</rows>
                <cols>3</cols>
                <dt>f</dt>
                <data>
                  -7.33813477e+001 1.28759628e+002 -1.61964607e+001</data></dipPosition>
              <pipPosition type_id="opencv-matrix">
                <rows>1</rows>
                <cols>3</cols>
                <dt>f</dt>
                <data>
                  -7.78385544e+001 1.42507904e+002 -3.42956009e+001</data></pipPosition>
              <mcpPosition type_id="opencv-matrix">
                <rows>1</rows>
                <cols>3</cols>
                <dt>f</dt>
                <data>
                  -6.49297409e+001 1.75486694e+002 -1.73523884e+001</data></mcpPosition></Middle>
            <Ring>
              <Type>3</Type>
              <isExtended>0</isExtended>
              <TipPosition type_id="opencv-matrix">
                <rows>1</rows>
                <cols>3</cols>
                <dt>f</dt>
                <data>
                  -5.69672737e+001 1.27896812e+002 -4.64267492e+000</data></TipPosition>
              <TipDirection type_id="opencv-matrix">
                <rows>1</rows>
                <cols>3</cols>
                <dt>f</dt>
                <data>
                  4.27576639e-002 -5.86304247e-001 8.08961749e-001</data></TipDirection>
              <TipVelocity type_id="opencv-matrix">
                <rows>1</rows>
                <cols>3</cols>
                <dt>f</dt>
                <data>
                  7.25260544e+001 -9.68413067e+000 7.94466019e+001</data></TipVelocity>
              <TipLength>5.2477397918701172e+001</TipLength>
              <dipPosition type_id="opencv-matrix">
                <rows>1</rows>
                <cols>3</cols>
                <dt>f</dt>
                <data>
                  -5.98310699e+001 1.28867584e+002 -1.56929111e+001</data></dipPosition>
              <pipPosition type_id="opencv-matrix">
                <rows>1</rows>
                <cols>3</cols>
                <dt>f</dt>
                <data>
                  -6.07958336e+001 1.42096634e+002 -3.39458809e+001</data></pipPosition>
              <mcpPosition type_id="opencv-matrix">
                <rows>1</rows>
                <cols>3</cols>
                <dt>f</dt>
                <data>
                  -4.67757912e+001 1.71693649e+002 -1.80770779e+001</data></mcpPosition></Ring>
            <Pinky>
              <Type>4</Type>
              <isExtended>1</isExtended>
              <TipPosition type_id="opencv-matrix">
                <rows>1</rows>
                <cols>3</cols>
                <dt>f</dt>
                <data>
                  -3.86963806e+001 1.48015869e+002 -7.11351929e+001</data></TipPosition>
              <TipDirection type_id="opencv-matrix">
                <rows>1</rows>
                <cols>3</cols>
                <dt>f</dt>
                <data>
                  -1.73001602e-001 -3.30002010e-001 -9.27991986e-001</data></TipDirection>
              <TipVelocity type_id="opencv-matrix">
                <rows>1</rows>
                <cols>3</cols>
                <dt>f</dt>
                <data>
                  -1.57381601e+001 -6.18990021e+001 4.09334564e+001</data></TipVelocity>
              <TipLength>4.1141311645507813e+001</TipLength>
              <dipPosition type_id="opencv-matrix">
                <rows>1</rows>
                <cols>3</cols>
                <dt>f</dt>
                <data>
                  -3.66561165e+001 1.52391891e+002 -6.15188484e+001</data></dipPosition>
              <pipPosition type_id="opencv-matrix">
                <rows>1</rows>
                <cols>3</cols>
                <dt>f</dt>
                <data>
                  -3.39000702e+001 1.57649063e+002 -4.67352257e+001</data></pipPosition>
              <mcpPosition type_id="opencv-matrix">
                <rows>1</rows>
                <cols>3</cols>
                <dt>f</dt>
                <data>
                  -3.09970264e+001 1.64306351e+002 -1.88657150e+001</data></mcpPosition></Pinky></Fingers></Right></Hands></RigthImage>
    <LeftImage>
      <Hands>
        <nHands>1</nHands>
        <Right>
          <Center type_id="opencv-matrix">
            <rows>1</rows>
            <cols>3</cols>
            <dt>f</dt>
            <data>
              -5.89856300e+001 1.61372528e+002 -3.13172722e+000</data></Center>
          <Normal type_id="opencv-matrix">
            <rows>1</rows>
            <cols>3</cols>
            <dt>f</dt>
            <data>
              -1.95793584e-001 -8.40599716e-001 -5.05031645e-001</data></Normal>
          <Direction type_id="opencv-matrix">
            <rows>1</rows>
            <cols>3</cols>
            <dt>f</dt>
            <data>
              -2.09386364e-001 5.38958371e-001 -8.15892875e-001</data></Direction>
          <Velocity type_id="opencv-matrix">
            <rows>1</rows>
            <cols>3</cols>
            <dt>f</dt>
            <data>
              9.61543732e+001 -8.18312740e+000 6.61570892e+001</data></Velocity>
          <SphereCenter type_id="opencv-matrix">
            <rows>1</rows>
            <cols>3</cols>
            <dt>f</dt>
            <data>
              -8.81571579e+001 1.41621048e+002 -2.52005215e+001</data></SphereCenter>
          <Confidence>7.8935933113098145e-001</Confidence>
          <PinchStrength>0.</PinchStrength>
          <GrabStrength>3.7596240639686584e-001</GrabStrength>
          <SphereRadius>4.2725090026855469e+001</SphereRadius>
          <Fingers>
            <nFingers>5</nFingers>
            <Thumb>
              <Type>0</Type>
              <isExtended>1</isExtended>
              <TipPosition type_id="opencv-matrix">
                <rows>1</rows>
                <cols>3</cols>
                <dt>f</dt>
                <data>
                  -1.36189072e+002 1.54973999e+002 -6.45511329e-001</data></TipPosition>
              <TipDirection type_id="opencv-matrix">
                <rows>1</rows>
                <cols>3</cols>
                <dt>f</dt>
                <data>
                  -8.70011151e-001 2.78747350e-001 -4.06670064e-001</data></TipDirection>
              <TipVelocity type_id="opencv-matrix">
                <rows>1</rows>
                <cols>3</cols>
                <dt>f</dt>
                <data>
                  8.74364319e+001 5.60648918e+001 2.02645126e+002</data></TipVelocity>
              <TipLength>4.2449111938476562e+001</TipLength>
              <dipPosition type_id="opencv-matrix">
                <rows>1</rows>
                <cols>3</cols>
                <dt>f</dt>
                <data>
                  -1.22956001e+002 1.50613007e+002 3.33959699e+000</data></dipPosition>
              <pipPosition type_id="opencv-matrix">
                <rows>1</rows>
                <cols>3</cols>
                <dt>f</dt>
                <data>
                  -9.87948532e+001 1.42871902e+002 1.46332636e+001</data></pipPosition>
              <mcpPosition type_id="opencv-matrix">
                <rows>1</rows>
                <cols>3</cols>
                <dt>f</dt>
                <data>
                  -6.65231857e+001 1.32647064e+002 3.71517220e+001</data></mcpPosition></Thumb>
            <Index>
              <Type>1</Type>
              <isExtended>0</isExtended>
              <TipPosition type_id="opencv-matrix">
                <rows>1</rows>
                <cols>3</cols>
                <dt>f</dt>
                <data>
                  -7.92801285e+001 1.33877945e+002 -4.74600267e+000</data></TipPosition>
              <TipDirection type_id="opencv-matrix">
                <rows>1</rows>
                <cols>3</cols>
                <dt>f</dt>
                <data>
                  2.81607807e-001 -5.55764198e-001 7.82191277e-001</data></TipDirection>
              <TipVelocity type_id="opencv-matrix">
                <rows>1</rows>
                <cols>3</cols>
                <dt>f</dt>
                <data>
                  7.46353455e+001 4.47875977e+000 1.09914169e+002</data></TipVelocity>
              <TipLength>4.7899085998535156e+001</TipLength>
              <dipPosition type_id="opencv-matrix">
                <rows>1</rows>
                <cols>3</cols>
                <dt>f</dt>
                <data>
                  -8.29361496e+001 1.33888336e+002 -1.45152073e+001</data></dipPosition>
              <pipPosition type_id="opencv-matrix">
                <rows>1</rows>
                <cols>3</cols>
                <dt>f</dt>
                <data>
                  -8.84801483e+001 1.44829620e+002 -2.99141617e+001</data></pipPosition>
              <mcpPosition type_id="opencv-matrix">
                <rows>1</rows>
                <cols>3</cols>
                <dt>f</dt>
                <data>
                  -8.24410172e+001 1.74927765e+002 -1.31168127e+001</data></mcpPosition></Index>
            <Middle>
              <Type>2</Type>
              <isExtended>0</isExtended>
              <TipPosition type_id="opencv-matrix">
                <rows>1</rows>
                <cols>3</cols>
                <dt>f</dt>
                <data>
                  -6.92076187e+001 1.27979904e+002 -5.23018837e+000</data></TipPosition>
              <TipDirection type_id="opencv-matrix">
                <rows>1</rows>
                <cols>3</cols>
                <dt>f</dt>
                <data>
                  1.92439452e-001 -5.93580365e-001 7.81427801e-001</data></TipDirection>
              <TipVelocity type_id="opencv-matrix">
                <rows>1</rows>
                <cols>3</cols>
                <dt>f</dt>
                <data>
                  7.04503937e+001 -2.37938404e+000 9.74600754e+001</data></TipVelocity>
              <TipLength>5.4577163696289062e+001</TipLength>
              <dipPosition type_id="opencv-matrix">
                <rows>1</rows>
                <cols>3</cols>
                <dt>f</dt>
                <data>
                  -7.33813477e+001 1.28759628e+002 -1.61964607e+001</data></dipPosition>
              <pipPosition type_id="opencv-matrix">
                <rows>1</rows>
                <cols>3</cols>
                <dt>f</dt>
                <data>
                  -7.78385544e+001 1.42507904e+002 -3.42956009e+001</data></pipPosition>
              <mcpPosition type_id="opencv-matrix">
                <rows>1</rows>
                <cols>3</cols>
                <dt>f</dt>
                <data>
                  -6.49297409e+001 1.75486694e+002 -1.73523884e+001</data></mcpPosition></Middle>
            <Ring>
              <Type>3</Type>
              <isExtended>0</isExtended>
              <TipPosition type_id="opencv-matrix">
                <rows>1</rows>
                <cols>3</cols>
                <dt>f</dt>
                <data>
                  -5.69672737e+001 1.27896812e+002 -4.64267492e+000</data></TipPosition>
              <TipDirection type_id="opencv-matrix">
                <rows>1</rows>
                <cols>3</cols>
                <dt>f</dt>
                <data>
                  4.27576639e-002 -5.86304247e-001 8.08961749e-001</data></TipDirection>
              <TipVelocity type_id="opencv-matrix">
                <rows>1</rows>
                <cols>3</cols>
                <dt>f</dt>
                <data>
                  7.25260544e+001 -9.68413067e+000 7.94466019e+001</data></TipVelocity>
              <TipLength>5.2477397918701172e+001</TipLength>
              <dipPosition type_id="opencv-matrix">
                <rows>1</rows>
                <cols>3</cols>
                <dt>f</dt>
                <data>
                  -5.98310699e+001 1.28867584e+002 -1.56929111e+001</data></dipPosition>
              <pipPosition type_id="opencv-matrix">
                <rows>1</rows>
                <cols>3</cols>
                <dt>f</dt>
                <data>
                  -6.07958336e+001 1.42096634e+002 -3.39458809e+001</data></pipPosition>
              <mcpPosition type_id="opencv-matrix">
                <rows>1</rows>
                <cols>3</cols>
                <dt>f</dt>
                <data>
                  -4.67757912e+001 1.71693649e+002 -1.80770779e+001</data></mcpPosition></Ring>
            <Pinky>
              <Type>4</Type>
              <isExtended>1</isExtended>
              <TipPosition type_id="opencv-matrix">
                <rows>1</rows>
                <cols>3</cols>
                <dt>f</dt>
                <data>
                  -3.86963806e+001 1.48015869e+002 -7.11351929e+001</data></TipPosition>
              <TipDirection type_id="opencv-matrix">
                <rows>1</rows>
                <cols>3</cols>
                <dt>f</dt>
                <data>
                  -1.73001602e-001 -3.30002010e-001 -9.27991986e-001</data></TipDirection>
              <TipVelocity type_id="opencv-matrix">
                <rows>1</rows>
                <cols>3</cols>
                <dt>f</dt>
                <data>
                  -1.57381601e+001 -6.18990021e+001 4.09334564e+001</data></TipVelocity>
              <TipLength>4.1141311645507813e+001</TipLength>
              <dipPosition type_id="opencv-matrix">
                <rows>1</rows>
                <cols>3</cols>
                <dt>f</dt>
                <data>
                  -3.66561165e+001 1.52391891e+002 -6.15188484e+001</data></dipPosition>
              <pipPosition type_id="opencv-matrix">
                <rows>1</rows>
                <cols>3</cols>
                <dt>f</dt>
                <data>
                  -3.39000702e+001 1.57649063e+002 -4.67352257e+001</data></pipPosition>
              <mcpPosition type_id="opencv-matrix">
                <rows>1</rows>
                <cols>3</cols>
                <dt>f</dt>
                <data>
                  -3.09970264e+001 1.64306351e+002 -1.88657150e+001</data></mcpPosition></Pinky></Fingers></Right></Hands></LeftImage></Images></Frame>
</opencv_storage>
