{"table":[{"type":"2DTouch2","count":0,"x":[212,278],"y":[7,26]},{"type":"2DTouch2","count":1,"x":[212,278],"y":[8,27]},{"type":"2DTouch2","count":2,"x":[211,278],"y":[8,29]},{"type":"2DTouch2","count":3,"x":[211,279],"y":[9,30]},{"type":"2DTouch2","count":4,"x":[210,280],"y":[9,31]},{"type":"2DTouch2","count":5,"x":[210,280],"y":[10,31]},{"type":"2DTouch2","count":6,"x":[210,280],"y":[10,32]},{"type":"2DTouch2","count":7,"x":[211,281],"y":[12,34]},{"type":"2DTouch2","count":8,"x":[211,282],"y":[12,36]},{"type":"2DTouch2","count":9,"x":[212,283],"y":[13,39]},{"type":"2DTouch2","count":10,"x":[212,283],"y":[16,41]},{"type":"2DTouch2","count":11,"x":[211,283],"y":[16,42]},{"type":"2DTouch2","count":12,"x":[211,283],"y":[18,43]},{"type":"2DTouch2","count":13,"x":[210,282],"y":[27,48]},{"type":"2DTouch2","count":14,"x":[207,281],"y":[34,53]},{"type":"2DTouch2","count":15,"x":[209,280],"y":[36,56]},{"type":"2DTouch2","count":16,"x":[205,279],"y":[41,60]},{"type":"2DTouch2","count":17,"x":[201,278],"y":[51,68]},{"type":"2DTouch2","count":18,"x":[200,277],"y":[58,75]},{"type":"2DTouch2","count":19,"x":[202,275],"y":[63,83]},{"type":"2DTouch2","count":20,"x":[200,271],"y":[73,91]},{"type":"2DTouch2","count":21,"x":[195,268],"y":[84,98]},{"type":"2DTouch2","count":22,"x":[194,268],"y":[90,105]},{"type":"2DTouch2","count":23,"x":[191,267],"y":[95,113]},{"type":"2DTouch2","count":24,"x":[188,264],"y":[106,123]},{"type":"2DTouch2","count":25,"x":[187,263],"y":[116,130]},{"type":"2DTouch2","count":26,"x":[186,262],"y":[125,139]},{"type":"2DTouch2","count":27,"x":[184,261],"y":[135,150]},{"type":"2DTouch2","count":28,"x":[184,261],"y":[146,159]},{"type":"2DTouch2","count":29,"x":[184,261],"y":[155,169]},{"type":"2DTouch2","count":30,"x":[182,260],"y":[164,180]},{"type":"2DTouch2","count":31,"x":[182,261],"y":[173,189]},{"type":"2DTouch2","count":32,"x":[182,261],"y":[183,196]},{"type":"2DTouch2","count":33,"x":[181,261],"y":[187,203]},{"type":"2DTouch2","count":34,"x":[261,179],"y":[212,198]},{"type":"2DTouch2","count":35,"x":[260,181],"y":[219,206]},{"type":"2DTouch2","count":36,"x":[262,181],"y":[227,215]},{"type":"2DTouch2","count":37,"x":[262,180],"y":[237,224]},{"type":"2DTouch2","count":38,"x":[262,180],"y":[247,234]},{"type":"2DTouch2","count":39,"x":[263,181],"y":[257,245]},{"type":"2DTouch2","count":40,"x":[263,180],"y":[267,255]},{"type":"2DTouch2","count":41,"x":[261,179],"y":[278,266]},{"type":"2DTouch2","count":42,"x":[263,180],"y":[286,276]},{"type":"2DTouch2","count":43,"x":[263,180],"y":[295,284]},{"type":"2DTouch2","count":44,"x":[262,179],"y":[306,296]},{"type":"2DTouch2","count":45,"x":[262,179],"y":[316,307]},{"type":"2DTouch2","count":46,"x":[263,179],"y":[325,318]},{"type":"2DTouch2","count":47,"x":[262,177],"y":[334,328]},{"type":"2DTouch2","count":48,"x":[262,178],"y":[343,333]},{"type":"2DTouch2","count":49,"x":[262,179],"y":[348,338]},{"type":"2DTouch2","count":50,"x":[262,178],"y":[352,343]},{"type":"2DTouch2","count":51,"x":[262,178],"y":[359,349]},{"type":"2DTouch2","count":52,"x":[261,176],"y":[368,357]},{"type":"2DTouch2","count":53,"x":[260,177],"y":[375,365]},{"type":"2DTouch2","count":54,"x":[260,177],"y":[376,368]},{"type":"2DTouch2","count":55,"x":[260,178],"y":[376,368]},{"type":"2DTouch2","count":56,"x":[260,178],"y":[377,369]},{"type":"2DTouch2","count":57,"x":[260,178],"y":[379,371]},{"type":"2DTouch2","count":58,"x":[261,179],"y":[382,379]},{"type":"2DTouch2","count":59,"x":[261,179],"y":[382,381]}]}