{"table":[{"type":"2DTouch3","count":0,"x":[257,180,348],"y":[319,377,335]},{"type":"2DTouch3","count":1,"x":[254,178,347],"y":[312,370,328]},{"type":"2DTouch3","count":2,"x":[253,178,345],"y":[307,357,324]},{"type":"2DTouch3","count":3,"x":[253,180,343],"y":[301,348,318]},{"type":"2DTouch3","count":4,"x":[252,177,345],"y":[295,345,313]},{"type":"2DTouch3","count":5,"x":[250,175,345],"y":[292,341,307]},{"type":"2DTouch3","count":6,"x":[248,174,344],"y":[286,330,299]},{"type":"2DTouch3","count":7,"x":[247,171,341],"y":[280,320,292]},{"type":"2DTouch3","count":8,"x":[246,169,342],"y":[271,314,286]},{"type":"2DTouch3","count":9,"x":[243,168,342],"y":[263,310,280]},{"type":"2DTouch3","count":10,"x":[241,166,341],"y":[257,300,270]},{"type":"2DTouch3","count":11,"x":[240,167,340],"y":[249,289,262]},{"type":"2DTouch3","count":12,"x":[239,167,339],"y":[240,282,256]},{"type":"2DTouch3","count":13,"x":[238,166,338],"y":[231,278,250]},{"type":"2DTouch3","count":14,"x":[238,166,338],"y":[225,268,241]},{"type":"2DTouch3","count":15,"x":[239,166,338],"y":[219,258,232]},{"type":"2DTouch3","count":16,"x":[239,165,337],"y":[207,251,224]},{"type":"2DTouch3","count":17,"x":[239,164,336],"y":[197,247,214]},{"type":"2DTouch3","count":18,"x":[237,164,336],"y":[191,237,203]},{"type":"2DTouch3","count":19,"x":[235,164,336],"y":[182,225,195]},{"type":"2DTouch3","count":20,"x":[234,163,335],"y":[172,218,189]},{"type":"2DTouch3","count":21,"x":[234,163,336],"y":[166,211,185]},{"type":"2DTouch3","count":22,"x":[234,162,336],"y":[162,202,178]},{"type":"2DTouch3","count":23,"x":[234,165,336],"y":[155,192,169]},{"type":"2DTouch3","count":24,"x":[233,165,336],"y":[145,186,161]},{"type":"2DTouch3","count":25,"x":[232,163,337],"y":[135,181,154]},{"type":"2DTouch3","count":26,"x":[233,163,338],"y":[128,171,145]},{"type":"2DTouch3","count":27,"x":[232,165,338],"y":[118,159,135]},{"type":"2DTouch3","count":28,"x":[231,164,337],"y":[107,153,126]},{"type":"2DTouch3","count":29,"x":[232,163,337],"y":[99,145,118]},{"type":"2DTouch3","count":30,"x":[232,163,337],"y":[92,134,107]},{"type":"2DTouch3","count":31,"x":[234,162,335],"y":[84,123,99]},{"type":"2DTouch3","count":32,"x":[235,161,335],"y":[73,120,93]},{"type":"2DTouch3","count":33,"x":[236,161,336],"y":[68,114,89]},{"type":"2DTouch3","count":34,"x":[237,161,336],"y":[63,106,83]},{"type":"2DTouch3","count":35,"x":[238,163,336],"y":[58,102,76]},{"type":"2DTouch3","count":36,"x":[239,165,336],"y":[53,94,71]},{"type":"2DTouch3","count":37,"x":[240,164,335],"y":[47,91,69]},{"type":"2DTouch3","count":38,"x":[240,163,336],"y":[42,89,65]},{"type":"2DTouch3","count":39,"x":[242,164,338],"y":[38,88,62]},{"type":"2DTouch3","count":40,"x":[242,164,339],"y":[37,87,60]},{"type":"2DTouch3","count":41,"x":[243,165,340],"y":[35,85,59]},{"type":"2DTouch3","count":42,"x":[244,167,340],"y":[34,81,58]},{"type":"2DTouch3","count":43,"x":[242,167,340],"y":[34,77,57]},{"type":"2DTouch3","count":44,"x":[242,166,340],"y":[34,75,57]},{"type":"2DTouch3","count":45,"x":[243,165,340],"y":[34,76,58]},{"type":"2DTouch3","count":46,"x":[244,166,340],"y":[34,78,58]},{"type":"2DTouch3","count":47,"x":[244,164,341],"y":[34,79,59]},{"type":"2DTouch3","count":48,"x":[244,164,341],"y":[35,81,59]},{"type":"2DTouch3","count":49,"x":[244,164,340],"y":[35,83,60]}]}