{"table":[{"type":"2DTouch3","count":0,"x":[479,463,466],"y":[81,183,285]},{"type":"2DTouch3","count":1,"x":[479,464,467],"y":[81,183,285]},{"type":"2DTouch3","count":2,"x":[480,465,467],"y":[77,183,285]},{"type":"2DTouch3","count":3,"x":[481,465,468],"y":[75,184,285]},{"type":"2DTouch3","count":4,"x":[482,466,467],"y":[75,184,285]},{"type":"2DTouch3","count":5,"x":[482,466,467],"y":[76,184,285]},{"type":"2DTouch3","count":6,"x":[482,465,467],"y":[75,184,286]},{"type":"2DTouch3","count":7,"x":[482,465,467],"y":[74,184,286]},{"type":"2DTouch3","count":8,"x":[482,465,467],"y":[74,184,286]},{"type":"2DTouch3","count":9,"x":[482,465,467],"y":[75,184,286]},{"type":"2DTouch3","count":10,"x":[480,464,466],"y":[79,184,286]},{"type":"2DTouch3","count":11,"x":[478,464,467],"y":[82,184,285]},{"type":"2DTouch3","count":12,"x":[477,464,466],"y":[84,185,286]},{"type":"2DTouch3","count":13,"x":[474,461,462],"y":[82,185,283]},{"type":"2DTouch3","count":14,"x":[462,454,445],"y":[80,186,284]},{"type":"2DTouch3","count":15,"x":[449,442,434],"y":[83,189,285]},{"type":"2DTouch3","count":16,"x":[437,430,422],"y":[86,189,286]},{"type":"2DTouch3","count":17,"x":[425,422,404],"y":[84,186,291]},{"type":"2DTouch3","count":18,"x":[417,413,397],"y":[83,188,286]},{"type":"2DTouch3","count":19,"x":[407,405,391],"y":[83,188,282]},{"type":"2DTouch3","count":20,"x":[397,394,383],"y":[79,185,282]},{"type":"2DTouch3","count":21,"x":[388,387,370],"y":[76,183,283]},{"type":"2DTouch3","count":22,"x":[381,376,362],"y":[76,184,280]},{"type":"2DTouch3","count":23,"x":[371,366,354],"y":[75,184,279]},{"type":"2DTouch3","count":24,"x":[360,357,343],"y":[72,180,281]},{"type":"2DTouch3","count":25,"x":[350,347,333],"y":[73,181,279]},{"type":"2DTouch3","count":26,"x":[339,334,322],"y":[71,181,277]},{"type":"2DTouch3","count":27,"x":[325,322,310],"y":[70,181,276]},{"type":"2DTouch3","count":28,"x":[310,309,298],"y":[70,181,273]},{"type":"2DTouch3","count":29,"x":[295,297,286],"y":[69,178,272]},{"type":"2DTouch3","count":30,"x":[281,282,272],"y":[70,178,271]},{"type":"2DTouch3","count":31,"x":[269,269,261],"y":[67,175,270]},{"type":"2DTouch3","count":32,"x":[258,256,246],"y":[65,173,269]},{"type":"2DTouch3","count":33,"x":[243,242,232],"y":[64,171,268]},{"type":"2DTouch3","count":34,"x":[229,228,216],"y":[62,171,267]},{"type":"2DTouch3","count":35,"x":[216,214,203],"y":[61,172,266]},{"type":"2DTouch3","count":36,"x":[201,200,190],"y":[60,170,265]},{"type":"2DTouch3","count":37,"x":[185,183,176],"y":[60,170,264]},{"type":"2DTouch3","count":38,"x":[170,168,163],"y":[58,168,263]},{"type":"2DTouch3","count":39,"x":[155,153,148],"y":[58,168,264]},{"type":"2DTouch3","count":40,"x":[139,138,133],"y":[57,167,264]},{"type":"2DTouch3","count":41,"x":[126,125,118],"y":[57,168,264]},{"type":"2DTouch3","count":42,"x":[111,112,106],"y":[58,167,263]},{"type":"2DTouch3","count":43,"x":[98,98,93],"y":[58,166,264]},{"type":"2DTouch3","count":44,"x":[86,86,82],"y":[59,167,263]},{"type":"2DTouch3","count":45,"x":[74,76,73],"y":[58,165,262]},{"type":"2DTouch3","count":46,"x":[64,65,61],"y":[58,167,262]},{"type":"2DTouch3","count":47,"x":[54,55,52],"y":[59,168,263]},{"type":"2DTouch3","count":48,"x":[45,49,46],"y":[58,167,263]},{"type":"2DTouch3","count":49,"x":[40,43,40],"y":[58,166,262]},{"type":"2DTouch3","count":50,"x":[35,38,33],"y":[59,166,264]},{"type":"2DTouch3","count":51,"x":[28,34,21],"y":[61,168,265]},{"type":"2DTouch3","count":52,"x":[15,26,10],"y":[64,172,265]},{"type":"2DTouch3","count":53,"x":[8,21,5],"y":[65,173,265]},{"type":"2DTouch3","count":54,"x":[8,20,5],"y":[64,173,265]},{"type":"2DTouch3","count":55,"x":[9,20,5],"y":[63,173,265]},{"type":"2DTouch3","count":56,"x":[8,20,4],"y":[65,173,265]},{"type":"2DTouch3","count":57,"x":[9,21,4],"y":[66,172,266]},{"type":"2DTouch3","count":58,"x":[11,22,4],"y":[64,172,266]},{"type":"2DTouch3","count":59,"x":[9,24,4],"y":[66,172,266]}]}