{"table":[{"type":"2DTouch2","count":0,"x":[311,218],"y":[221,126]},{"type":"2DTouch2","count":1,"x":[311,217],"y":[229,126]},{"type":"2DTouch2","count":2,"x":[207,334],"y":[115,218]},{"type":"2DTouch2","count":3,"x":[197,333],"y":[105,223]},{"type":"2DTouch2","count":4,"x":[192,333],"y":[103,233]},{"type":"2DTouch2","count":5,"x":[189,344],"y":[103,243]},{"type":"2DTouch2","count":6,"x":[188,357],"y":[102,244]},{"type":"2DTouch2","count":7,"x":[189,369],"y":[102,251]},{"type":"2DTouch2","count":8,"x":[188,371],"y":[101,261]},{"type":"2DTouch3","count":9,"x":[187,379,376],"y":[97,259,274]},{"type":"2DTouch2","count":10,"x":[174,379],"y":[84,278]},{"type":"2DTouch2","count":11,"x":[162,382],"y":[76,277]},{"type":"2DTouch2","count":12,"x":[159,388],"y":[76,269]},{"type":"2DTouch2","count":13,"x":[155,397],"y":[73,276]},{"type":"2DTouch2","count":14,"x":[146,406],"y":[68,283]},{"type":"2DTouch2","count":15,"x":[138,409],"y":[62,285]},{"type":"2DTouch2","count":16,"x":[135,405],"y":[60,287]},{"type":"2DTouch2","count":17,"x":[131,410],"y":[58,294]},{"type":"2DTouch2","count":18,"x":[124,417],"y":[55,300]},{"type":"2DTouch2","count":19,"x":[119,426],"y":[52,300]},{"type":"2DTouch2","count":20,"x":[108,430],"y":[47,304]},{"type":"2DTouch3","count":21,"x":[91,429,411],"y":[42,303,326]},{"type":"2DTouch3","count":22,"x":[80,429,411],"y":[38,304,325]},{"type":"2DTouch3","count":23,"x":[78,430,412],"y":[37,304,325]},{"type":"2DTouch2","count":24,"x":[72,437],"y":[36,311]},{"type":"2DTouch2","count":25,"x":[71,443],"y":[36,316]},{"type":"2DTouch2","count":26,"x":[71,445],"y":[35,318]},{"type":"2DTouch2","count":27,"x":[62,444],"y":[34,318]},{"type":"2DTouch2","count":28,"x":[53,444],"y":[29,317]},{"type":"2DTouch2","count":29,"x":[50,448],"y":[26,313]},{"type":"2DTouch2","count":30,"x":[50,452],"y":[27,314]},{"type":"2DTouch2","count":31,"x":[51,443],"y":[28,328]},{"type":"2DTouch2","count":32,"x":[52,438],"y":[29,332]},{"type":"2DTouch2","count":33,"x":[53,439],"y":[29,331]},{"type":"2DTouch2","count":34,"x":[52,439],"y":[29,330]},{"type":"2DTouch2","count":35,"x":[53,440],"y":[29,328]},{"type":"2DTouch2","count":36,"x":[53,450],"y":[29,317]},{"type":"2DTouch2","count":37,"x":[53,454],"y":[29,312]},{"type":"2DTouch2","count":38,"x":[54,444],"y":[29,324]},{"type":"2DTouch2","count":39,"x":[54,439],"y":[29,331]},{"type":"2DTouch2","count":40,"x":[54,438],"y":[29,331]},{"type":"2DTouch2","count":41,"x":[54,438],"y":[30,330]},{"type":"2DTouch2","count":42,"x":[54,446],"y":[30,321]},{"type":"2DTouch2","count":43,"x":[54,454],"y":[29,313]},{"type":"2DTouch2","count":44,"x":[54,454],"y":[29,313]},{"type":"2DTouch2","count":45,"x":[54,454],"y":[30,312]},{"type":"2DTouch2","count":46,"x":[55,444],"y":[30,324]},{"type":"2DTouch2","count":47,"x":[54,439],"y":[30,328]},{"type":"2DTouch2","count":48,"x":[54,450],"y":[31,317]},{"type":"2DTouch2","count":49,"x":[55,454],"y":[31,312]}]}